{
	"groupLibName": "index",
	"groupSubjectType": "library",	
	"list":
	[
		{
			"name": "Coding"
		},
		{
			"name": "Engineering",
			"notImplemented": true
		},
		{
			"name": "Aptitude & Reasoning",
			"subjectType": "topic",
			"notImplemented": true
		},
		{
			"name": "English",
			"subjectType": "topic",
			"notImplemented": true
		},
		{
			"name": "Mathematics",
			"notImplemented": true
		},
		{
			"name": "General Knowledge",
			"subjectType": "topic",
			"notImplemented": true
		},
		{
			"name": "MBA",
			"notImplemented": true
		},
		{
			"name": "Science",
			"notImplemented": true
		}
	]
}